pygments_renderer/__init__.py
pygments_renderer/apps.py
pygments_renderer/templatetags/__init__.py
pygments_renderer/templatetags/pygmentize.py
django_pygments_renderer-0.0.1.dist-info/LICENSE
django_pygments_renderer-0.0.1.dist-info/METADATA
django_pygments_renderer-0.0.1.dist-info/WHEEL
django_pygments_renderer-0.0.1.dist-info/top_level.txt
django_pygments_renderer-0.0.1.dist-info/RECORD
