Metadata-Version: 2.1
Name: django-pygments-renderer
Version: 0.0.1
Summary: Provides functionality for syntax highlighting using Pygments.
Home-page: https://github.com/c-bata/django-pygments-renderer
Author: Masashi Shibata
Author-email: contact@c-bata.link
License: MIT
Platform: UNKNOWN
Requires-Dist: Django
Requires-Dist: pygments
